aeon/__init__.py
aeon/anomaly_detection/__init__.py
aeon/anomaly_detection/base.py
aeon/anomaly_detection/collection/__init__.py
aeon/anomaly_detection/collection/_classification.py
aeon/anomaly_detection/collection/_outlier_detection.py
aeon/anomaly_detection/collection/base.py
aeon/anomaly_detection/series/__init__.py
aeon/anomaly_detection/series/_pyodadapter.py
aeon/anomaly_detection/series/base.py
aeon/anomaly_detection/series/distance_based/__init__.py
aeon/anomaly_detection/series/distance_based/_cblof.py
aeon/anomaly_detection/series/distance_based/_kmeans.py
aeon/anomaly_detection/series/distance_based/_left_stampi.py
aeon/anomaly_detection/series/distance_based/_lof.py
aeon/anomaly_detection/series/distance_based/_merlin.py
aeon/anomaly_detection/series/distance_based/_rockad.py
aeon/anomaly_detection/series/distance_based/_stomp.py
aeon/anomaly_detection/series/distance_based/tests/__init__.py
aeon/anomaly_detection/series/distance_based/tests/test_cblof.py
aeon/anomaly_detection/series/distance_based/tests/test_kmeans.py
aeon/anomaly_detection/series/distance_based/tests/test_left_stampi.py
aeon/anomaly_detection/series/distance_based/tests/test_lof.py
aeon/anomaly_detection/series/distance_based/tests/test_merlin.py
aeon/anomaly_detection/series/distance_based/tests/test_rockad.py
aeon/anomaly_detection/series/distance_based/tests/test_stomp.py
aeon/anomaly_detection/series/distribution_based/__init__.py
aeon/anomaly_detection/series/distribution_based/_copod.py
aeon/anomaly_detection/series/distribution_based/_dwt_mlead.py
aeon/anomaly_detection/series/distribution_based/tests/__init__.py
aeon/anomaly_detection/series/distribution_based/tests/test_copod.py
aeon/anomaly_detection/series/distribution_based/tests/test_dwt_mlead.py
aeon/anomaly_detection/series/outlier_detection/__init__.py
aeon/anomaly_detection/series/outlier_detection/_iforest.py
aeon/anomaly_detection/series/outlier_detection/_one_class_svm.py
aeon-1.3.0.dist-info/licenses/LICENSE
aeon-1.3.0.dist-info/METADATA
aeon-1.3.0.dist-info/WHEEL
aeon-1.3.0.dist-info/top_level.txt
aeon-1.3.0.dist-info/zip-safe
aeon-1.3.0.dist-info/RECORD
