Metadata-Version: 2.4
Name: aeon
Version: 1.3.0
Summary: A toolkit for time series machine learning
Author-email: aeon developers <contact@aeon-toolkit.org>
Maintainer-email: aeon developers <contact@aeon-toolkit.org>
License: BSD 3-Clause License
Project-URL: Homepage, https://www.aeon-toolkit.org
Project-URL: Repository, https://github.com/aeon-toolkit/aeon
Project-URL: Documentation, https://www.aeon-toolkit.org
Project-URL: Changelog, https://www.aeon-toolkit.org/en/stable/changelog.html
Project-URL: Download, https://pypi.org/project/aeon/#files
Project-URL: API, https://www.aeon-toolkit.org/en/stable/api_reference.html
Keywords: data-science,machine-learning,data-mining,time-series,scikit-learn,forecasting,time-series-analysis,time-series-classification,time-series-clustering,time-series-regression
Classifier: Intended Audience :: Science/Research
Classifier: Intended Audience :: Developers
Classifier: Programming Language :: Python
Classifier: Topic :: Software Development
Classifier: Topic :: Scientific/Engineering
Classifier: Development Status :: 5 - Production/Stable
Classifier: Operating System :: Microsoft :: Windows
Classifier: Operating System :: POSIX
Classifier: Operating System :: Unix
Classifier: Operating System :: MacOS
Classifier: Programming Language :: Python :: 3
Classifier: Programming Language :: Python :: 3.10
Classifier: Programming Language :: Python :: 3.11
Classifier: Programming Language :: Python :: 3.12
Classifier: Programming Language :: Python :: 3.13
Requires-Python: <3.14,>=3.10
License-File: LICENSE
Requires-Dist: deprecated>=1.2.13
Requires-Dist: numba<0.62.0,>=0.55
Requires-Dist: numpy<2.3.0,>=1.21.0
Requires-Dist: packaging>=20.0
Requires-Dist: pandas<2.4.0,>=2.0.0
Requires-Dist: scikit-learn<1.8.0,>=1.0.0
Requires-Dist: scipy<1.16.0,>=1.9.0
Requires-Dist: typing-extensions>=4.6.0
Provides-Extra: all-extras
Requires-Dist: esig>=1.0.0; platform_system != "Darwin" and extra == "all-extras"
Requires-Dist: imbalanced-learn; extra == "all-extras"
Requires-Dist: matplotlib>=3.3.2; extra == "all-extras"
Requires-Dist: pycatch22>=0.4.5; extra == "all-extras"
Requires-Dist: pyod>=1.1.3; extra == "all-extras"
Requires-Dist: pydot>=2.0.0; extra == "all-extras"
Requires-Dist: seaborn>=0.11.0; extra == "all-extras"
Requires-Dist: sparse; extra == "all-extras"
Requires-Dist: statsmodels>=0.12.1; extra == "all-extras"
Requires-Dist: stumpy>=1.5.1; extra == "all-extras"
Requires-Dist: tensorflow>=2.14; python_version < "3.13" and extra == "all-extras"
Requires-Dist: keras>=3.6.0; python_version < "3.13" and extra == "all-extras"
Requires-Dist: torch>=1.13.1; extra == "all-extras"
Requires-Dist: tsfresh>=0.20.0; extra == "all-extras"
Requires-Dist: tslearn>=0.5.2; extra == "all-extras"
Provides-Extra: dl
Requires-Dist: tensorflow>=2.14; python_version < "3.13" and extra == "dl"
Requires-Dist: keras>=3.6.0; python_version < "3.13" and extra == "dl"
Provides-Extra: unstable-extras
Requires-Dist: mrsqm<0.1.0,>=0.0.7; (platform_system != "Windows" and python_version < "3.12") and extra == "unstable-extras"
Requires-Dist: mrseql<0.1.0,>=0.0.4; (platform_system != "Windows" and python_version < "3.12") and extra == "unstable-extras"
Provides-Extra: dev
Requires-Dist: pre-commit; extra == "dev"
Requires-Dist: pytest; extra == "dev"
Requires-Dist: pytest-cov; extra == "dev"
Requires-Dist: pytest-doctestplus; extra == "dev"
Requires-Dist: pytest-mock; extra == "dev"
Requires-Dist: pytest-randomly; extra == "dev"
Requires-Dist: pytest-remotedata; extra == "dev"
Requires-Dist: pytest-rerunfailures<17.0; extra == "dev"
Requires-Dist: pytest-timeout; extra == "dev"
Requires-Dist: pytest-xdist[psutil]; extra == "dev"
Provides-Extra: binder
Requires-Dist: notebook; extra == "binder"
Requires-Dist: jupyterlab; extra == "binder"
Provides-Extra: docs
Requires-Dist: sphinx<8.3.0; extra == "docs"
Requires-Dist: sphinx-design; extra == "docs"
Requires-Dist: sphinx-version-warning; extra == "docs"
Requires-Dist: sphinx_issues; extra == "docs"
Requires-Dist: sphinx-copybutton; extra == "docs"
Requires-Dist: sphinxext-opengraph[social_cards]; extra == "docs"
Requires-Dist: nbsphinx; extra == "docs"
Requires-Dist: numpydoc; extra == "docs"
Requires-Dist: myst-parser; extra == "docs"
Requires-Dist: jupyter; extra == "docs"
Requires-Dist: furo; extra == "docs"
Requires-Dist: tabulate; extra == "docs"
Requires-Dist: matplotlib; extra == "docs"
Dynamic: license-file
